CHANGELOG.txt
LICENCE.txt
MANIFEST.in
README.txt
__init__.py
setup.py
steps.txt
youtube_api.egg-info/SOURCES.txt
youtube_api.egg-info/dependency_links.txt
youtube_api.egg-info/requires.txt
youtube_api.egg-info/top_level.txt
youtube_api/Lib/site-packages/_virtualenv.py
youtube_api/Lib/site-packages/pyparsing.py
youtube_api/Lib/site-packages/six.py
youtube_api/Lib/site-packages/zipp.py
youtube_api/Lib/site-packages/Pygments-2.10.0.dist-info/entry_points.txt
youtube_api/Lib/site-packages/Pygments-2.10.0.dist-info/top_level.txt
youtube_api/Lib/site-packages/_distutils_hack/__init__.py
youtube_api/Lib/site-packages/_distutils_hack/override.py
youtube_api/Lib/site-packages/beautifulsoup4-4.10.0.dist-info/COPYING.txt
youtube_api/Lib/site-packages/beautifulsoup4-4.10.0.dist-info/top_level.txt
youtube_api/Lib/site-packages/bleach/__init__.py
youtube_api/Lib/site-packages/bleach/callbacks.py
youtube_api/Lib/site-packages/bleach/html5lib_shim.py
youtube_api/Lib/site-packages/bleach/linkifier.py
youtube_api/Lib/site-packages/bleach/sanitizer.py
youtube_api/Lib/site-packages/bleach/utils.py
youtube_api/Lib/site-packages/bleach-4.1.0.dist-info/top_level.txt
youtube_api/Lib/site-packages/bleach/_vendor/__init__.py
youtube_api/Lib/site-packages/bleach/_vendor/parse.py
youtube_api/Lib/site-packages/bleach/_vendor/vendor.txt
youtube_api/Lib/site-packages/bleach/_vendor/html5lib/__init__.py
youtube_api/Lib/site-packages/bleach/_vendor/html5lib/_ihatexml.py
youtube_api/Lib/site-packages/bleach/_vendor/html5lib/_inputstream.py
youtube_api/Lib/site-packages/bleach/_vendor/html5lib/_tokenizer.py
youtube_api/Lib/site-packages/bleach/_vendor/html5lib/_utils.py
youtube_api/Lib/site-packages/bleach/_vendor/html5lib/constants.py
youtube_api/Lib/site-packages/bleach/_vendor/html5lib/html5parser.py
youtube_api/Lib/site-packages/bleach/_vendor/html5lib/serializer.py
youtube_api/Lib/site-packages/bleach/_vendor/html5lib-1.1.dist-info/top_level.txt
youtube_api/Lib/site-packages/bleach/_vendor/html5lib/_trie/__init__.py
youtube_api/Lib/site-packages/bleach/_vendor/html5lib/_trie/_base.py
youtube_api/Lib/site-packages/bleach/_vendor/html5lib/_trie/py.py
youtube_api/Lib/site-packages/bleach/_vendor/html5lib/filters/__init__.py
youtube_api/Lib/site-packages/bleach/_vendor/html5lib/filters/alphabeticalattributes.py
youtube_api/Lib/site-packages/bleach/_vendor/html5lib/filters/base.py
youtube_api/Lib/site-packages/bleach/_vendor/html5lib/filters/inject_meta_charset.py
youtube_api/Lib/site-packages/bleach/_vendor/html5lib/filters/lint.py
youtube_api/Lib/site-packages/bs4-0.0.1.dist-info/top_level.txt
youtube_api/Lib/site-packages/certifi-2021.10.8.dist-info/top_level.txt
youtube_api/Lib/site-packages/charset_normalizer-2.0.7.dist-info/entry_points.txt
youtube_api/Lib/site-packages/charset_normalizer-2.0.7.dist-info/top_level.txt
youtube_api/Lib/site-packages/colorama-0.4.4.dist-info/LICENSE.txt
youtube_api/Lib/site-packages/colorama-0.4.4.dist-info/top_level.txt
youtube_api/Lib/site-packages/docutils-0.18.dist-info/COPYING.txt
youtube_api/Lib/site-packages/docutils-0.18.dist-info/top_level.txt
youtube_api/Lib/site-packages/idna-3.3.dist-info/top_level.txt
youtube_api/Lib/site-packages/importlib_metadata-4.8.2.dist-info/top_level.txt
youtube_api/Lib/site-packages/keyring-23.2.1.dist-info/entry_points.txt
youtube_api/Lib/site-packages/keyring-23.2.1.dist-info/top_level.txt
youtube_api/Lib/site-packages/packaging-21.2.dist-info/top_level.txt
youtube_api/Lib/site-packages/pip-21.3.1.dist-info/LICENSE.txt
youtube_api/Lib/site-packages/pip-21.3.1.dist-info/entry_points.txt
youtube_api/Lib/site-packages/pip-21.3.1.dist-info/top_level.txt
youtube_api/Lib/site-packages/pkginfo-1.7.1.dist-info/LICENSE.txt
youtube_api/Lib/site-packages/pkginfo-1.7.1.dist-info/entry_points.txt
youtube_api/Lib/site-packages/pkginfo-1.7.1.dist-info/top_level.txt
youtube_api/Lib/site-packages/pyparsing-2.4.7.dist-info/top_level.txt
youtube_api/Lib/site-packages/pywin32_ctypes-0.2.0.dist-info/LICENSE.txt
youtube_api/Lib/site-packages/pywin32_ctypes-0.2.0.dist-info/top_level.txt
youtube_api/Lib/site-packages/readme_renderer-30.0.dist-info/entry_points.txt
youtube_api/Lib/site-packages/readme_renderer-30.0.dist-info/top_level.txt
youtube_api/Lib/site-packages/requests-2.26.0.dist-info/top_level.txt
youtube_api/Lib/site-packages/requests_toolbelt-0.9.1.dist-info/top_level.txt
youtube_api/Lib/site-packages/rfc3986-1.5.0.dist-info/top_level.txt
youtube_api/Lib/site-packages/setuptools-58.3.0.dist-info/entry_points.txt
youtube_api/Lib/site-packages/setuptools-58.3.0.dist-info/top_level.txt
youtube_api/Lib/site-packages/six-1.16.0.dist-info/top_level.txt
youtube_api/Lib/site-packages/soupsieve-2.3.1.dist-info/top_level.txt
youtube_api/Lib/site-packages/tqdm-4.62.3.dist-info/entry_points.txt
youtube_api/Lib/site-packages/tqdm-4.62.3.dist-info/top_level.txt
youtube_api/Lib/site-packages/twine-3.6.0.dist-info/entry_points.txt
youtube_api/Lib/site-packages/twine-3.6.0.dist-info/top_level.txt
youtube_api/Lib/site-packages/urllib3-1.26.7.dist-info/LICENSE.txt
youtube_api/Lib/site-packages/urllib3-1.26.7.dist-info/top_level.txt
youtube_api/Lib/site-packages/webencodings-0.5.1.dist-info/top_level.txt
youtube_api/Lib/site-packages/wheel-0.37.0.dist-info/LICENSE.txt
youtube_api/Lib/site-packages/wheel-0.37.0.dist-info/entry_points.txt
youtube_api/Lib/site-packages/wheel-0.37.0.dist-info/top_level.txt
youtube_api/Lib/site-packages/zipp-3.6.0.dist-info/top_level.txt
youtube_api_basic.egg-info/PKG-INFO
youtube_api_basic.egg-info/SOURCES.txt
youtube_api_basic.egg-info/dependency_links.txt
youtube_api_basic.egg-info/requires.txt
youtube_api_basic.egg-info/top_level.txt