Metadata-Version: 2.1
Name: youtube-api-basic
Version: 0.0.1
Summary: a very basic youtube api
Home-page: UNKNOWN
Author: khalil el ghoul
Author-email: khalilelghoul01@gmail.com
License: MIT
Keywords: youtube
Platform: UNKNOWN
Classifier: Development Status :: 5 - Production/Stable
Classifier: Intended Audience :: Education
Classifier: Operating System :: Microsoft :: Windows :: Windows 10
Classifier: License :: OSI Approved :: MIT License
Classifier: Programming Language :: Python :: 3
License-File: LICENCE.txt
